openmonkeymind/__init__.py
openmonkeymind/_base_omm_plugin.py
openmonkeymind/_baseopenmonkeymind.py
openmonkeymind/_dummymonkeymind.py
openmonkeymind/_exceptions.py
openmonkeymind/_omm_log_backend.py
openmonkeymind/_openmonkeymind.py
openmonkeymind-0.1.0.data/data/share/opensesame_extensions/OpenMonkeyMind/OpenMonkeyMind.py
openmonkeymind-0.1.0.data/data/share/opensesame_extensions/OpenMonkeyMind/info.yaml
openmonkeymind-0.1.0.data/data/share/opensesame_extensions/OpenMonkeyMind/omm-entry-point.osexp
openmonkeymind-0.1.0.data/data/share/opensesame_extensions/OpenMonkeyMind/omm-template.osexp
openmonkeymind-0.1.0.data/data/share/opensesame_extensions/OpenMonkeyMind/openmonkeymind.ui
openmonkeymind-0.1.0.data/data/share/opensesame_plugins/OMMAnnounce/OMMAnnounce.png
openmonkeymind-0.1.0.data/data/share/opensesame_plugins/OMMAnnounce/OMMAnnounce.py
openmonkeymind-0.1.0.data/data/share/opensesame_plugins/OMMAnnounce/OMMAnnounce_large.png
openmonkeymind-0.1.0.data/data/share/opensesame_plugins/OMMAnnounce/info.yaml
openmonkeymind-0.1.0.data/data/share/opensesame_plugins/OMMConditioner/OMMConditioner.png
openmonkeymind-0.1.0.data/data/share/opensesame_plugins/OMMConditioner/OMMConditioner.py
openmonkeymind-0.1.0.data/data/share/opensesame_plugins/OMMConditioner/OMMConditioner_large.png
openmonkeymind-0.1.0.data/data/share/opensesame_plugins/OMMConditioner/info.yaml
openmonkeymind-0.1.0.data/data/share/opensesame_plugins/OMMConditioner/conditioners/__init__.py
openmonkeymind-0.1.0.data/data/share/opensesame_plugins/OMMConditioner/conditioners/_base_conditioner.py
openmonkeymind-0.1.0.data/data/share/opensesame_plugins/OMMConditioner/conditioners/_dummy.py
openmonkeymind-0.1.0.data/data/share/opensesame_plugins/OMMConditioner/conditioners/_seed_dispenser.py
openmonkeymind-0.1.0.data/data/share/opensesame_plugins/OMMDetectParticipant/OMMDetectParticipant.png
openmonkeymind-0.1.0.data/data/share/opensesame_plugins/OMMDetectParticipant/OMMDetectParticipant.py
openmonkeymind-0.1.0.dist-info/COPYING
openmonkeymind-0.1.0.dist-info/METADATA
openmonkeymind-0.1.0.dist-info/WHEEL
openmonkeymind-0.1.0.dist-info/top_level.txt
openmonkeymind-0.1.0.dist-info/RECORD
