Metadata-Version: 2.1
Name: openmonkeymind
Version: 0.1.0
Summary: OpenMonkeyMind plugins and extension for OpenSesame
Home-page: https://github.com/open-cogsci/omm-client
Author: Sebastiaan Mathot
Author-email: s.mathot@cogsci.nl
License: UNKNOWN
Platform: UNKNOWN
Classifier: Intended Audience :: Science/Research
Classifier: Topic :: Scientific/Engineering
Classifier: Environment :: MacOS X
Classifier: Environment :: Win32 (MS Windows)
Classifier: Environment :: X11 Applications
Classifier: License :: OSI Approved :: Apache Software License
Classifier: Programming Language :: Python :: 2
